ys_portal_gun/__init__.py
ys_portal_gun/__main__.py
ys_portal_gun/main.py
ys_portal_gun-0.1.1.dist-info/WHEEL
ys_portal_gun-0.1.1.dist-info/entry_points.txt
ys_portal_gun-0.1.1.dist-info/METADATA
ys_portal_gun-0.1.1.dist-info/RECORD
