Metadata-Version: 2.3
Name: ys-portal-gun
Version: 0.1.1
Summary: Add your description here
Requires-Dist: typer>=0.16.0
Requires-Python: >=3.13
